digitales_belegblatt/__init__.py
digitales_belegblatt/digitales_belegblatt.py
digitales_belegblatt-2.4.0.dist-info/METADATA
digitales_belegblatt-2.4.0.dist-info/WHEEL
digitales_belegblatt-2.4.0.dist-info/top_level.txt
digitales_belegblatt-2.4.0.dist-info/RECORD
